{
    "URL": "admin/internal/middleware",
    "parent": "",
    "controller": {
        "_is_func": true,
        "args": [],
        "javascript": ""
    },
    "code": {
        "widgets": {
            "52xpJloT": {
                "slots": {
                    "events": []
                },
                "widget": "middleware_listing"
            }
        },
        "slotAssignments": {
            "body": [
                "52xpJloT"
            ]
        }
    },
    "Title": "",
    "contentType": ""
}